uniPairs/__init__.py
uniPairs/estimator.py
unipairs-0.1.4.dist-info/METADATA
unipairs-0.1.4.dist-info/WHEEL
unipairs-0.1.4.dist-info/top_level.txt
unipairs-0.1.4.dist-info/RECORD
