Metadata-Version: 2.4
Name: uniPairs
Version: 0.1.4
Summary: Univariate-Guided Interaction Modeling
Author: Aymen Echarghaoui
License: MIT
Keywords: lasso,unilasso,interactions,regression
Classifier: Programming Language :: Python :: 3
Classifier: License :: OSI Approved :: MIT License
Classifier: Intended Audience :: Science/Research
Classifier: Topic :: Scientific/Engineering
Requires-Python: >=3.9
Requires-Dist: numpy>=1.20
Requires-Dist: scipy>=1.7
Requires-Dist: scikit-learn>=1.0
Requires-Dist: matplotlib>=3.4
Requires-Dist: seaborn>=0.11
Requires-Dist: adelie>=1.1.52
